robustranking/__init__.py
robustranking/benchmark.py
robustranking/comparison/__init__.py
robustranking/comparison/abstract_comparison.py
robustranking/comparison/aggregated_comparison.py
robustranking/comparison/bootstrap_comparison.py
robustranking/comparison/mo_bootstrap_comparison.py
robustranking/comparison/mo_domination_bootstrap_comparison.py
robustranking/comparison/ranked_comparison.py
robustranking/utils/__init__.py
robustranking/utils/metrics.py
robustranking/utils/multiobjective.py
robustranking/utils/plots.py
robustranking-0.2.dist-info/LICENSE.md
robustranking-0.2.dist-info/METADATA
robustranking-0.2.dist-info/WHEEL
robustranking-0.2.dist-info/top_level.txt
robustranking-0.2.dist-info/RECORD
