Metadata-Version: 2.1
Name: robustranking
Version: 0.2
Summary: Package for ranking algorithms
Author-email: Jeroen Rook <j.g.rook@utwente.nl>
Maintainer-email: Jeroen Rook <j.g.rook@utwente.nl>
Project-URL: Homepage, https://github.com/jeroenrook/robustranking
Project-URL: Repository, https://github.com/jeroenrook/robustranking
Requires-Python: >=3.9
License-File: LICENSE.md
Requires-Dist: matplotlib>=3.5.2
Requires-Dist: numpy>=1.23
Requires-Dist: pandas
Requires-Dist: scipy
Requires-Dist: statsmodels
Requires-Dist: typing_extensions
Provides-Extra: dev
Requires-Dist: pytest; extra == "dev"
Requires-Dist: flake8; extra == "dev"
Requires-Dist: flake8-docstrings; extra == "dev"
Requires-Dist: flake8-import-order; extra == "dev"
Requires-Dist: pre-commit; extra == "dev"
Requires-Dist: pylint; extra == "dev"
Requires-Dist: YAPF; extra == "dev"
Requires-Dist: isort; extra == "dev"
